mcp_server_vss/__init__.py
mcp_server_vss/__main__.py
mcp_server_vss/client.py
mcp_server_vss/exceptions.py
mcp_server_vss/server.py
mcp_server_vss/models/__init__.py
mcp_server_vss/models/backups.py
mcp_server_vss/models/billing.py
mcp_server_vss/models/requests.py
mcp_server_vss/models/vms.py
mcp_server_vss/prompts/__init__.py
mcp_server_vss/prompts/backups.py
mcp_server_vss/prompts/common.py
mcp_server_vss/prompts/vms.py
mcp_server_vss/tools/common.py
mcp_server_vss/tools/backups/__init__.py
mcp_server_vss/tools/backups/host_sessions.py
mcp_server_vss/tools/billing/__init__.py
mcp_server_vss/tools/billing/get_billing_details.py
mcp_server_vss/tools/billing/invoice.py
mcp_server_vss/tools/billing/payment.py
mcp_server_vss/tools/vms/__init__.py
mcp_server_vss/tools/vms/disks.py
mcp_server_vss/tools/vms/get_vm_console.py
mcp_server_vss/tools/vms/get_vm_info.py
mcp_server_vss/tools/vms/get_vm_performance_metrics.py
mcp_server_vss/tools/vms/power_control.py
mcp_server_vss/tools/vms/resize_vm_resources.py
mcp_server_vss/tools/vms/snapshots.py
mcp_server_vss/tools/vms/utls.py
mcp_vss-2025.7.0.dev0.dist-info/METADATA
mcp_vss-2025.7.0.dev0.dist-info/WHEEL
mcp_vss-2025.7.0.dev0.dist-info/entry_points.txt
mcp_vss-2025.7.0.dev0.dist-info/licenses/LICENSE.md
mcp_vss-2025.7.0.dev0.dist-info/RECORD
