Metadata-Version: 2.4
Name: mcp-vss
Version: 2025.7.0.dev0
Summary: MCP server for the ITS Private Cloud
License-File: LICENSE.md
Requires-Python: >=3.10
Requires-Dist: click>=8.1.8
Requires-Dist: dataclasses-json>=0.6.7
Requires-Dist: fastmcp>=2.5.2
Requires-Dist: httpx>=0.28.1
Requires-Dist: loguru>=0.7.3
Requires-Dist: mcp[cli]>=1.7.1
Requires-Dist: pydantic-settings>=2.9.1
Requires-Dist: pydantic>=2.11.4
Requires-Dist: python-dateutil>=2.9.0.post0
Requires-Dist: starlette>=0.46.2
